simpellab/__init__.py
simpellab/settings.py
simpellab/setup.py
simpellab/version.py
simpellab/mod_base/__init__.py
simpellab/mod_base/admin.py
simpellab/mod_base/apps.py
simpellab/mod_base/forms.py
simpellab/mod_base/helpers.py
simpellab/mod_base/hooks.py
simpellab/mod_base/models.py
simpellab/mod_base/names.py
simpellab/mod_base/resources.py
simpellab/mod_base/views.py
simpellab/mod_base/management/__init__.py
simpellab/mod_base/management/commands/__init__.py
simpellab/mod_base/management/commands/reset_simpellab.py
simpellab/mod_base/migrations/0001_initial.py
simpellab/mod_base/migrations/__init__.py
simpellab/mod_blueprints/__init__.py
simpellab/mod_blueprints/admin.py
simpellab/mod_blueprints/apps.py
simpellab/mod_blueprints/managers.py
simpellab/mod_blueprints/models.py
simpellab/mod_blueprints/migrations/0001_initial.py
simpellab/mod_blueprints/migrations/__init__.py
simpellab/mod_blueprints/templates/admin/cart.html
simpellab/mod_calibration/__init__.py
simpellab/mod_calibration/admin.py
simpellab/mod_calibration/apps.py
simpellab/mod_calibration/hooks.py
simpellab/mod_calibration/models.py
simpellab/mod_calibration/resources.py
simpellab/mod_calibration/migrations/0001_initial.py
simpellab/mod_calibration/migrations/0002_calibrationtask.py
simpellab/mod_calibration/migrations/0003_calibrationservice_analysis_method.py
simpellab/mod_calibration/migrations/__init__.py
simpellab/mod_calibration/templates/mod_calibration/certificate.html
simpellab/mod_calibration/tests/__init__.py
simpellab/mod_calibration/tests/factories.py
simpellab/mod_calibration/tests/tests_models.py
simpellab/mod_certification/__init__.py
simpellab/mod_certification/admin.py
simpellab/mod_certification/apps.py
simpellab/mod_certification/hooks.py
simpellab/mod_certification/models.py
simpellab/mod_certification/resources.py
simpellab/mod_certification/migrations/0001_initial.py
simpellab/mod_certification/migrations/0002_certificationtask.py
simpellab-1.0.1.dist-info/LICENSE
simpellab-1.0.1.dist-info/METADATA
simpellab-1.0.1.dist-info/WHEEL
simpellab-1.0.1.dist-info/top_level.txt
simpellab-1.0.1.dist-info/RECORD
